CHANGES.txt
LICENSE.txt
MANIFEST.in
README.txt
setup.py
Django_Drupal_Password_Hasher.egg-info/PKG-INFO
Django_Drupal_Password_Hasher.egg-info/SOURCES.txt
Django_Drupal_Password_Hasher.egg-info/dependency_links.txt
Django_Drupal_Password_Hasher.egg-info/requires.txt
Django_Drupal_Password_Hasher.egg-info/top_level.txt
djangodrupalpasswordhasher/__init__.py
djangodrupalpasswordhasher/drupal_password_hasher.py
djangodrupalpasswordhasher/test/__init__.py
djangodrupalpasswordhasher/test/test_drupal_password_hasher.py