Metadata-Version: 1.0
Name: Django-Drupal-Password-Hasher
Version: 0.1.1
Summary: Useful password hasher for django sites with drupal components
Home-page: http://pypi.python.org/pypi/Django-drupal-password-hasher/
Author: ARC Staff, pberndt
Author-email: consultants@pdx.edu
License: LICENSE.txt
Platform: UNKNOWN
